test/__init__.py
test/test_vtide.py
test/utils/__init__.py
test/utils/test_utils.py
vtide/__init__.py
vtide/vtide.py
vtide/utils/__init__.py
vtide/utils/utils.py
vtide-0.1.0.dist-info/METADATA
vtide-0.1.0.dist-info/WHEEL
vtide-0.1.0.dist-info/top_level.txt
vtide-0.1.0.dist-info/RECORD
