Metadata-Version: 2.2
Name: vtide
Version: 0.1.0
Summary: VTide: A python package for variational Bayesian tidal harmonic analysis 
Home-page: https://github.com/thomasmonahan/VTide
Author: Thomas Monahan
Author-email: thomas.monahan@eng.ox.ac.uk
Classifier: Programming Language :: Python :: 3
Classifier: License :: OSI Approved :: MIT License
Classifier: Operating System :: OS Independent
Requires-Python: >=3.6
Requires-Dist: numpy
Requires-Dist: pandas
Requires-Dist: utide
Requires-Dist: scipy
Requires-Dist: matplotlib
Dynamic: author
Dynamic: author-email
Dynamic: classifier
Dynamic: description
Dynamic: description-content-type
Dynamic: home-page
Dynamic: requires-dist
Dynamic: requires-python
Dynamic: summary
